stirling/__init__.py
stirling/stirling.py
stirling/version.py
stirling-1.2.1.dist-info/LICENSE.txt
stirling-1.2.1.dist-info/METADATA
stirling-1.2.1.dist-info/WHEEL
stirling-1.2.1.dist-info/top_level.txt
stirling-1.2.1.dist-info/zip-safe
stirling-1.2.1.dist-info/RECORD
