Metadata-Version: 2.1
Name: stirling
Version: 1.2.1
Summary: Set partitioning
Home-page: https://github.com/rob-smallshire/stirling
Author: Robert Smallshire
Author-email: robert+stirling@smallshire.org.uk
License: MIT License
Keywords: sets partitioning
Classifier: Development Status :: 5 - Production/Stable
Classifier: Intended Audience :: Developers
Classifier: Topic :: Software Development :: Libraries :: Python Modules
Classifier: License :: OSI Approved :: MIT License
Classifier: Programming Language :: Python :: 3 :: Only
Classifier: Programming Language :: Python :: 3.10
Classifier: Programming Language :: Python :: 3.11
License-File: LICENSE.txt
Provides-Extra: dev
Requires-Dist: bumpversion ; extra == 'dev'
Provides-Extra: test
Requires-Dist: pytest ; extra == 'test'
